Workbook

Sheet Contenido
B5: DIAGNÓSTICO DEL NIVEL DE IMPLEMENTACIÓN DEL SISTEMA INTEGRADO DE GESTIÓN | C5: Contexto de la Organización | D5: Liderazgo | E5: Planificación | F5: Apoyo | G5: Operación | H5: Evaluación del Desempeño | I5: Mejora | J5: CUMPLE
B6: RESULTADO ESPERADO | C6: 0.98 | D6: 0.98 | E6: 0.98 | F6: 0.98 | G6: 0.98 | H6: 0.98 | I6: 0.98 | J6: 0.98
A7: GC | B7: GESTIÓN DE LA CALIDAD | C7: =+SGC!G41 | D7: =+SGC!G86 | E7: =+SGC!G131 | F7: =+SGC!G226 | G7: =+SGC!G424 -> - | H7: =+SGC!G491 | I7: =+SGC!G522 | J7: =+IFERROR(+AVERAGE(C7,D7,E7,F7,G7,H7,I7),"")
A8: GMA | B8: GESTIÓN MEDIOAMBIENTAL | C8: =+SGA!G37 | D8: =+SGA!G69 | E8: =+SGA!G139 | F8: =+SGA!G203 | G8: =+SGA!G229 | H8: =+SGA!G297 | I8: =+SGA!G322 | J8: =+IFERROR(+AVERAGE(C8,D8,E8,F8,G8,H8,I8),"")
A9: GSST | B9: GESTIÓN DE LA SEGURIDAD Y SALUD EN EL TRABAJO | C9: =+SST!G25 | D9: =+SST!G72 | E9: =+SST!G146 | F9: =+SST!G212 | G9: =+SST!G270 | H9: =+SST!G322 | I9: =+SST!G350 | J9: =+IFERROR(+AVERAGE(C9,D9,E9,F9,G9,H9,I9),"")
B15: DESARROLLADO POR

Sheet SGC
B1: DIAGNÓSTICO PREVIO - SGC. ISO 9001:2015 | D1: ÍNDICE
A3: 4 | B3: CONTEXTO DE LA ORGANIZACIÓN
A4: 4.1 | B4: Comprensión de la organización y su contexto
A5: 1 | B5: La organización ha determinado las cuestiones externas e internas que son pertinentes para su propósito y su dirección estratégica. | D5: =+IF(C5="","",+IF(C5=0,"No Cumple",+IF(C5=1,"Cumple Parcial",+IF(C5=2,"Cumple Completo",+IF(C5="N","NA")))))
A6: =1+A5 -> 2 | B6: La organización hace seguimiento y revisa la información sobre estas cuestiones externas e internas. | D6: =+IF(C6="","",+IF(C6=0,"No Cumple",+IF(C6=1,"Cumple Parcial",+IF(C6=2,"Cumple Completo",+IF(C6="N","NA")))))
C7: =SUM(C5:C6) -> 0 | D7: =+COUNT(C5:C6)*2 -> 0 | E7: =+IF(C5="","",C7/D7)
A9: 4.2 | B9: Comprensión de las necesidades y expectativas de las partes interesadas
A10: =1+A6 -> 3 | B10: la organización determina las partes interesadas que son pertinentes al SGC | D10: =+IF(C10="","",+IF(C10=0,"No Cumple",+IF(C10=1,"Cumple Parcial",+IF(C10=2,"Cumple Completo",+IF(C10="N","NA")))))
A11: =1+A10 -> 4 | B11: La organización determina los requisitos de sus partes interesadas para el SGC | D11: =+IF(C11="","",+IF(C11=0,"No Cumple",+IF(C11=1,"Cumple Parcial",+IF(C11=2,"Cumple Completo",+IF(C11="N","NA")))))
A12: =1+A11 -> 5 | B12: La organización hace seguimiento y revisión de la información de sus partes interesadas y su requisitos pertinentes. | D12: =+IF(C12="","",+IF(C12=0,"No Cumple",+IF(C12=1,"Cumple Parcial",+IF(C12=2,"Cumple Completo",+IF(C12="N","NA")))))
C13: =SUM(C10:C12) -> 0 | D13: =+COUNT(C10:C12)*2 -> 0 | E13: =+IF(C10="","",C13/D13)
A15: 4.3 | B15: Determinación del alcance del sistema de gestión de la calidad
A16: =1+A12 -> 6 | B16: La organización determina los límites y la aplicabilidad del SGC para establecer su alcance. | D16: =+IF(C16="","",+IF(C16=0,"No Cumple",+IF(C16=1,"Cumple Parcial",+IF(C16=2,"Cumple Completo",+IF(C16="N","NA")))))
A17: =1+A16 -> 7 | B17: Al determinar el alcance, la organización considera: | D17: =+IF(C17="","",+IF(C17=0,"No Cumple",+IF(C17=1,"Cumple Parcial",+IF(C17=2,"Cumple Completo",+IF(C17="N","NA")))))
A18: =1+A17 -> 8 | B18: a) Las cuestiones externas e internas que son pertinentes. | D18: =+IF(C18="","",+IF(C18=0,"No Cumple",+IF(C18=1,"Cumple Parcial",+IF(C18=2,"Cumple Completo",+IF(C18="N","NA")))))
A19: =1+A18 -> 9 | B19: b) Los requisitos de las partes interesadas pertinentes. | D19: =+IF(C19="","",+IF(C19=0,"No Cumple",+IF(C19=1,"Cumple Parcial",+IF(C19=2,"Cumple Completo",+IF(C19="N","NA")))))
A20: =1+A19 -> 10 | B20: c) Los productos y servicios de la organización | D20: =+IF(C20="","",+IF(C20=0,"No Cumple",+IF(C20=1,"Cumple Parcial",+IF(C20=2,"Cumple Completo",+IF(C20="N","NA")))))
A21: =1+A20 -> 11 | B21: El alcance proporciona la justificación para cualquier requisito de esta Norma que la organización determine que no es aplicable para el alcance del SGC. | D21: =+IF(C21="","",+IF(C21=0,"No Cumple",+IF(C21=1,"Cumple Parcial",+IF(C21=2,"Cumple Completo",+IF(C21="N","NA")))))
A22: =1+A21 -> 12 | B22: La organización dispone y mantiene información documentada relacionada con el alcance del SGC. | D22: =+IF(C22="","",+IF(C22=0,"No Cumple",+IF(C22=1,"Cumple Parcial",+IF(C22=2,"Cumple Completo",+IF(C22="N","NA")))))
C23: =SUM(C16:C22) -> 0 | D23: =+COUNT(C16:C22)*2 -> 0 | E23: =+IF(C16="","",C23/D23)
A25: 4.4 | B25: Sistema de gestión de la calidad y sus procesos
A26: 4.4.1 | B26: Generalidades sobre gestión de procesos y mejora continua
A27: =1+A22 -> 13 | B27: La organización debe establecer, implementar, mantener y mejorar continuamente un SGC, incluidos los procesos y sus interacciones, de acuerdo a esta norma internacional, y debe: | D27: =+IF(C27="","",+IF(C27=0,"No Cumple",+IF(C27=1,"Cumple Parcial",+IF(C27=2,"Cumple Completo",+IF(C27="N","NA")))))
A28: =1+A27 -> 14 | B28: a) Determinar las entradas requeridas y las salidas esperadas de estos procesos | D28: =+IF(C28="","",+IF(C28=0,"No Cumple",+IF(C28=1,"Cumple Parcial",+IF(C28=2,"Cumple Completo",+IF(C28="N","NA")))))
A29: =1+A28 -> 15 | B29: b) Determinar la secuencia e interacción de los procesos | D29: =+IF(C29="","",+IF(C29=0,"No Cumple",+IF(C29=1,"Cumple Parcial",+IF(C29=2,"Cumple Completo",+IF(C29="N","NA")))))
A30: =1+A29 -> 16 | B30: c) Determinar y aplicar los criterios y los métodos (seguimiento, medición, indicadores del desempeño) | D30: =+IF(C30="","",+IF(C30=0,"No Cumple",+IF(C30=1,"Cumple Parcial",+IF(C30=2,"Cumple Completo",+IF(C30="N","NA")))))
A31: =1+A30 -> 17 | B31: d) Determinar los recursos necesarios para estos procesos y asegurarse de su disponibilidad | D31: =+IF(C31="","",+IF(C31=0,"No Cumple",+IF(C31=1,"Cumple Parcial",+IF(C31=2,"Cumple Completo",+IF(C31="N","NA")))))
A32: =1+A31 -> 18 | B32: e) Asignar las responsabilidades y autoridades para estos procesos | D32: =+IF(C32="","",+IF(C32=0,"No Cumple",+IF(C32=1,"Cumple Parcial",+IF(C32=2,"Cumple Completo",+IF(C32="N","NA")))))
A33: =1+A32 -> 19 | B33: f) Abordar los riesgos y oportunidades determinados de acuerdo con los requisitos del apartado 6.1 | D33: =+IF(C33="","",+IF(C33=0,"No Cumple",+IF(C33=1,"Cumple Parcial",+IF(C33=2,"Cumple Completo",+IF(C33="N","NA")))))
A34: =1+A33 -> 20 | B34: g) Evaluar estos procesos e implementar cualquier cambio necesario para asegurarse de que estos procesos logran los resultados previstos | D34: =+IF(C34="","",+IF(C34=0,"No Cumple",+IF(C34=1,"Cumple Parcial",+IF(C34=2,"Cumple Completo",+IF(C34="N","NA")))))
A35: =1+A34 -> 21 | B35: h) Mejorar los procesos y el sistema de gestión de la calidad | D35: =+IF(C35="","",+IF(C35=0,"No Cumple",+IF(C35=1,"Cumple Parcial",+IF(C35=2,"Cumple Completo",+IF(C35="N","NA")))))
C36: =SUM(C27:C35) -> 0 | D36: =+COUNT(C27:C35)*2 -> 0 | E36: =+IF(C27="","",C36/D36)
A38: 4.4.2 | B38: Documentación de los procesos del SGC
A39: =1+A35 -> 22 | B39: a) Mantener información documentada para apoya la operación de los procesos | D39: =+IF(C39="","",+IF(C39=0,"No Cumple",+IF(C39=1,"Cumple Parcial",+IF(C39=2,"Cumple Completo",+IF(C39="N","NA")))))
A40: =1+A39 -> 23 | B40: b) Conservar la información documentada para tener la confianza de que los procesos se realizan según lo planificado | D40: =+IF(C40="","",+IF(C40=0,"No Cumple",+IF(C40=1,"Cumple Parcial",+IF(C40=2,"Cumple Completo",+IF(C40="N","NA")))))
C41: =SUM(C39:C40) -> 0 | D41: =+COUNT(C39:C40)*2 -> 0 | E41: =+IF(C39="","",C41/D41) | G41: =IFERROR(+AVERAGE(E7,E13,E23,E36,E41),"")
A43: 5 | B43: LIDERAZGO
A44: 5.1 | B44: Liderazgo y compromiso
A45: 5.1.1 | B45: Generalidades
A46: =1+A40 -> 24 | B46: La alta dirección debe demostrar liderazgo y compromiso con respecto al SGC: | D46: =+IF(C46="","",+IF(C46=0,"No Cumple",+IF(C46=1,"Cumple Parcial",+IF(C46=2,"Cumple Completo",+IF(C46="N","NA")))))
A47: =1+A46 -> 25 | B47: a) asumiendo la responsabilidad y obligación de rendir cuentas con relación a la eficacia del SGC | D47: =+IF(C47="","",+IF(C47=0,"No Cumple",+IF(C47=1,"Cumple Parcial",+IF(C47=2,"Cumple Completo",+IF(C47="N","NA")))))
A48: =1+A47 -> 26 | B48: b) asegurándose de que se establezcan la política y los objetivos de la calidad para el SGC, y que estos sean compatibles con el contexto y la dirección estratégica de la organización | D48: =+IF(C48="","",+IF(C48=0,"No Cumple",+IF(C48=1,"Cumple Parcial",+IF(C48=2,"Cumple Completo",+IF(C48="N","NA")))))
A49: =1+A48 -> 27 | B49: c) asegurándose de la integración de los requisitos del SGC en los procesos de negocio de la organización | D49: =+IF(C49="","",+IF(C49=0,"No Cumple",+IF(C49=1,"Cumple Parcial",+IF(C49=2,"Cumple Completo",+IF(C49="N","NA")))))
A50: =1+A49 -> 28 | B50: d) promoviendo el uso del enfoque a procesos y el pensamiento basado en riesgos | D50: =+IF(C50="","",+IF(C50=0,"No Cumple",+IF(C50=1,"Cumple Parcial",+IF(C50=2,"Cumple Completo",+IF(C50="N","NA")))))
A51: =1+A50 -> 29 | B51: e) asegurándose de que los recursos necesarios para el SGC estén disponibles | D51: =+IF(C51="","",+IF(C51=0,"No Cumple",+IF(C51=1,"Cumple Parcial",+IF(C51=2,"Cumple Completo",+IF(C51="N","NA")))))
A52: =1+A51 -> 30 | B52: f) comunicando la importancia de una gestión de la calidad eficaz y de la conformidad con los requisitos del SGC | D52: =+IF(C52="","",+IF(C52=0,"No Cumple",+IF(C52=1,"Cumple Parcial",+IF(C52=2,"Cumple Completo",+IF(C52="N","NA")))))
A53: =1+A52 -> 31 | B53: g) asegurándose de que el SGC logre los resultados previstos | D53: =+IF(C53="","",+IF(C53=0,"No Cumple",+IF(C53=1,"Cumple Parcial",+IF(C53=2,"Cumple Completo",+IF(C53="N","NA")))))
A54: =1+A53 -> 32 | B54: h) comprometiendo, dirigiendo y apoyando a las personas, para contribuir a la eficacia del SGC | D54: =+IF(C54="","",+IF(C54=0,"No Cumple",+IF(C54=1,"Cumple Parcial",+IF(C54=2,"Cumple Completo",+IF(C54="N","NA")))))
A55: =1+A54 -> 33 | B55: i) Promoviendo la mejora | D55: =+IF(C55="","",+IF(C55=0,"No Cumple",+IF(C55=1,"Cumple Parcial",+IF(C55=2,"Cumple Completo",+IF(C55="N","NA")))))
A56: =1+A55 -> 34 | B56: j) apoyando otros roles pertinentes de la dirección, para demostrar su liderazgo en la forma en la que aplique a sus áreas de responsabilidad | D56: =+IF(C56="","",+IF(C56=0,"No Cumple",+IF(C56=1,"Cumple Parcial",+IF(C56=2,"Cumple Completo",+IF(C56="N","NA")))))
C57: =SUM(C46:C56) -> 0 | D57: =+COUNT(C46:C56)*2 -> 0 | E57: =+IF(C47="","",C57/D57)
A58: 5.1.2 | B58: Enfoque al Cliente
A59: =1+A56 -> 35 | B59: La dirección debe demostrar liderazgo y compromiso con respecto al enfoque al cliente, asegurándose de que: | D59: =+IF(C59="","",+IF(C59=0,"No Cumple",+IF(C59=1,"Cumple Parcial",+IF(C59=2,"Cumple Completo",+IF(C59="N","NA")))))
A60: =1+A59 -> 36 | B60: a) se determinan, comprometen y se cumplen regularmente los requisitos del cliente y los legales y reglamentarios aplicables | D60: =+IF(C60="","",+IF(C60=0,"No Cumple",+IF(C60=1,"Cumple Parcial",+IF(C60=2,"Cumple Completo",+IF(C60="N","NA")))))
A61: =1+A60 -> 37 | B61: b) se determinan y consideran los riesgos y oportunidades que pueden afectar a la conformidad de los productos y servicios y a la capacidad de aumentar la satisfacción del cliente | D61: =+IF(C61="","",+IF(C61=0,"No Cumple",+IF(C61=1,"Cumple Parcial",+IF(C61=2,"Cumple Completo",+IF(C61="N","NA")))))
A62: =1+A61 -> 38 | B62: c) se mantiene el enfoque en el aumento de la satisfacción del cliente | D62: =+IF(C62="","",+IF(C62=0,"No Cumple",+IF(C62=1,"Cumple Parcial",+IF(C62=2,"Cumple Completo",+IF(C62="N","NA")))))
C63: =SUM(C59:C62) -> 0 | D63: =+COUNT(C59:C62)*2 -> 0 | E63: =+IF(C60="","",C63/D63)
A64: 5.2 | B64: Política
A65: 5.2.1 | B65: Establecimiento de la política de la calidad
A66: =1+A62 -> 39 | B66: La alta dirección debe establecer, implementar y mantener una política de calidad que: | D66: =+IF(C66="","",+IF(C66=0,"No Cumple",+IF(C66=1,"Cumple Parcial",+IF(C66=2,"Cumple Completo",+IF(C66="N","NA")))))
A67: =1+A66 -> 40 | B67: a) sea apropiada al propósito y contexto de la organización y apoye su dirección estratégica | D67: =+IF(C67="","",+IF(C67=0,"No Cumple",+IF(C67=1,"Cumple Parcial",+IF(C67=2,"Cumple Completo",+IF(C67="N","NA")))))
A68: =1+A67 -> 41 | B68: b) proporcione un marco de referencia para el establecimiento de los objetivos de la calidad | D68: =+IF(C68="","",+IF(C68=0,"No Cumple",+IF(C68=1,"Cumple Parcial",+IF(C68=2,"Cumple Completo",+IF(C68="N","NA")))))
A69: =1+A68 -> 42 | B69: c) incluya un compromiso de cumplir requisitos aplicables | D69: =+IF(C69="","",+IF(C69=0,"No Cumple",+IF(C69=1,"Cumple Parcial",+IF(C69=2,"Cumple Completo",+IF(C69="N","NA")))))
A70: =1+A69 -> 43 | B70: d) incluya un compromiso de mejora continua del SGC | D70: =+IF(C70="","",+IF(C70=0,"No Cumple",+IF(C70=1,"Cumple Parcial",+IF(C70=2,"Cumple Completo",+IF(C70="N","NA")))))
C71: =SUM(C66:C70) -> 0 | D71: =+COUNT(C66:C70)*2 -> 0 | E71: =+IF(C66="","",C71/D71)
A72: 5.2.2 | B72: Comunicación de la política de la calidad
A73: =1+A70 -> 44 | B73: La política de calidad debe: | D73: =+IF(C73="","",+IF(C73=0,"No Cumple",+IF(C73=1,"Cumple Parcial",+IF(C73=2,"Cumple Completo",+IF(C73="N","NA")))))
A74: =1+A73 -> 45 | B74: a) estar disponible y mantenerse como información documentada | D74: =+IF(C74="","",+IF(C74=0,"No Cumple",+IF(C74=1,"Cumple Parcial",+IF(C74=2,"Cumple Completo",+IF(C74="N","NA")))))
A75: =1+A74 -> 46 | B75: b) comunicarse, entenderse y aplicarse dentro de la organización | D75: =+IF(C75="","",+IF(C75=0,"No Cumple",+IF(C75=1,"Cumple Parcial",+IF(C75=2,"Cumple Completo",+IF(C75="N","NA")))))
A76: =1+A75 -> 47 | B76: estar disponible para las partes interesadas pertinentes, según corresponda | D76: =+IF(C76="","",+IF(C76=0,"No Cumple",+IF(C76=1,"Cumple Parcial",+IF(C76=2,"Cumple Completo",+IF(C76="N","NA")))))
C77: =SUM(C73:C76) -> 0 | D77: =+COUNT(C73:C76)*2 -> 0 | E77: =+IF(C74="","",C77/D77)
A78: 5.3 | B78: Roles, responsabilidad y autoridades en la organización
A79: =1+A76 -> 48 | B79: La alta dirección debe asegurarse de que las responsabilidades y autoridades para los roles pertinentes se asignen, se comuniquen y se entienden en toda la organización. | D79: =+IF(C79="","",+IF(C79=0,"No Cumple",+IF(C79=1,"Cumple Parcial",+IF(C79=2,"Cumple Completo",+IF(C79="N","NA")))))
A80: =1+A79 -> 49 | B80: La alta dirección debe asignar la responsabilidad y autoridad para: | D80: =+IF(C80="","",+IF(C80=0,"No Cumple",+IF(C80=1,"Cumple Parcial",+IF(C80=2,"Cumple Completo",+IF(C80="N","NA")))))
A81: =1+A80 -> 50 | B81: a) asegurarse de que el SGC es conforme con los requisitos de esta Norma Internacional | D81: =+IF(C81="","",+IF(C81=0,"No Cumple",+IF(C81=1,"Cumple Parcial",+IF(C81=2,"Cumple Completo",+IF(C81="N","NA")))))
A82: =1+A81 -> 51 | B82: b) asegurarse de que los procesos están generando y proporcionando las salidas previstas | D82: =+IF(C82="","",+IF(C82=0,"No Cumple",+IF(C82=1,"Cumple Parcial",+IF(C82=2,"Cumple Completo",+IF(C82="N","NA")))))
A83: =1+A82 -> 52 | B83: c) informar, en particular, a la alta dirección sobre el desempeño del SGC y sobre las oportunidades de mejora (véase 10.1) | D83: =+IF(C83="","",+IF(C83=0,"No Cumple",+IF(C83=1,"Cumple Parcial",+IF(C83=2,"Cumple Completo",+IF(C83="N","NA")))))
A84: =1+A83 -> 53 | B84: d) asegurarse de que se promueve el enfoque al cliente en toda la organización | D84: =+IF(C84="","",+IF(C84=0,"No Cumple",+IF(C84=1,"Cumple Parcial",+IF(C84=2,"Cumple Completo",+IF(C84="N","NA")))))
A85: =1+A84 -> 54 | B85: e) asegurarse de que la integridad del SGC se mantiene cuando se planifican e implementan cambios en el SGC. | D85: =+IF(C85="","",+IF(C85=0,"No Cumple",+IF(C85=1,"Cumple Parcial",+IF(C85=2,"Cumple Completo",+IF(C85="N","NA")))))
C86: =SUM(C79:C85) -> 0 | D86: =+COUNT(C79:C85)*2 -> 0 | E86: =+IF(C79="","",C86/D86) | G86: =IFERROR(+AVERAGE(E57,E63,E71,E77,E86),"")
A87: 6 | B87: PLANIFICACIÓN
A88: 6.1 | B88: Acciones para abordar riesgos y oportunidades
A89: 6.1.1 | B89: Considerar cuestiones referidas en 4.1 y 4.2
A90: =1+A85 -> 55 | B90: Al planificar el SGC, la organización debe considerar las cuestiones referidas en el apartado 4.1 y los requisitos referidos en el apartado 4.2, y determinar los riesgos y oportunidades que es necesario abordar con el fin de: | D90: =+IF(C90="","",+IF(C90=0,"No Cumple",+IF(C90=1,"Cumple Parcial",+IF(C90=2,"Cumple Completo",+IF(C90="N","NA")))))
A91: =1+A90 -> 56 | B91: a) asegurar que el SGC puede lograr sus resultados previstos | D91: =+IF(C91="","",+IF(C91=0,"No Cumple",+IF(C91=1,"Cumple Parcial",+IF(C91=2,"Cumple Completo",+IF(C91="N","NA")))))
A92: =1+A91 -> 57 | B92: b) aumentar los efectos deseables | D92: =+IF(C92="","",+IF(C92=0,"No Cumple",+IF(C92=1,"Cumple Parcial",+IF(C92=2,"Cumple Completo",+IF(C92="N","NA")))))
A93: =1+A92 -> 58 | B93: c) prevenir o reducir efectos no deseados | D93: =+IF(C93="","",+IF(C93=0,"No Cumple",+IF(C93=1,"Cumple Parcial",+IF(C93=2,"Cumple Completo",+IF(C93="N","NA")))))
A94: =1+A93 -> 59 | B94: d) lograr la mejora | D94: =+IF(C94="","",+IF(C94=0,"No Cumple",+IF(C94=1,"Cumple Parcial",+IF(C94=2,"Cumple Completo",+IF(C94="N","NA")))))
C95: =SUM(C90:C94) -> 0 | D95: =+COUNT(C90:C94)*2 -> 0 | E95: =+IF(C90="","",C95/D95)
A96: 6.1.2 | B96: La organización debe planificar:
A97: =1+A94 -> 60 | B97: a) las acciones para abordar estos riesgos y oportunidades | D97: =+IF(C97="","",+IF(C97=0,"No Cumple",+IF(C97=1,"Cumple Parcial",+IF(C97=2,"Cumple Completo",+IF(C97="N","NA")))))
A98: =1+A97 -> 61 | B98: b) la manera de: | D98: =+IF(C98="","",+IF(C98=0,"No Cumple",+IF(C98=1,"Cumple Parcial",+IF(C98=2,"Cumple Completo",+IF(C98="N","NA")))))
A99: =1+A98 -> 62 | B99: 1) integrar e implementar las acciones en sus procesos del SGC (véase 4.4) | D99: =+IF(C99="","",+IF(C99=0,"No Cumple",+IF(C99=1,"Cumple Parcial",+IF(C99=2,"Cumple Completo",+IF(C99="N","NA")))))
A100: =1+A99 -> 63 | B100: 2) evaluar la eficacia de estas acciones | D100: =+IF(C100="","",+IF(C100=0,"No Cumple",+IF(C100=1,"Cumple Parcial",+IF(C100=2,"Cumple Completo",+IF(C100="N","NA")))))
A101: =1+A100 -> 64 | B101: Las acciones tomadas para abordar los riesgos y oportunidades deber ser proporcionales al impacto potencial en la conformidad de los productos y servicios | D101: =+IF(C101="","",+IF(C101=0,"No Cumple",+IF(C101=1,"Cumple Parcial",+IF(C101=2,"Cumple Completo",+IF(C101="N","NA")))))
C102: =SUM(C97:C101) -> 0 | D102: =+COUNT(C97:C101)*2 -> 0 | E102: =+IF(C97="","",C102/D102)
A103: 6.2 | B103: Objetivos de la calidad y planificación para lograrlos
A104: 6.2.1 | B104: Establecer objetivos
A105: =1+A101 -> 65 | B105: La organización debe establecer objetivos de la calidad para las funciones y niveles pertinentes y los procesos necesarios para el SGC. | D105: =+IF(C105="","",+IF(C105=0,"No Cumple",+IF(C105=1,"Cumple Parcial",+IF(C105=2,"Cumple Completo",+IF(C105="N","NA")))))
A106: =1+A105 -> 66 | B106: Los objetivos de la calidad deben: | D106: =+IF(C106="","",+IF(C106=0,"No Cumple",+IF(C106=1,"Cumple Parcial",+IF(C106=2,"Cumple Completo",+IF(C106="N","NA")))))
...

Sheet SGA
B1: DIAGNÓSTICO PREVIO - SGA. ISO 14001:2015 | D1: ÍNDICE
A3: 4 | B3: CONTEXTO DE LA ORGANIZACIÓN
A4: 4.1 | B4: Comprensión de la organización y su contexto
A5: 1 | B5: La organización ha determinado las cuestiones externas e internas que son pertinentes para su propósito y que afectan su capacidad para lograr los resultados previstos del SGA. | D5: =+IF(C5="","",+IF(C5=0,"No Cumple",+IF(C5=1,"Cumple Parcial",+IF(C5=2,"Cumple Completo",+IF(C5="N","NA")))))
A6: =1+A5 -> 2 | B6: La organización hace seguimiento y revisa la información sobre estas cuestiones externas e internas. | D6: =+IF(C6="","",+IF(C6=0,"No Cumple",+IF(C6=1,"Cumple Parcial",+IF(C6=2,"Cumple Completo",+IF(C6="N","NA")))))
C7: =SUM(C5:C6) -> 0 | D7: =+COUNT(C5:C6)*2 -> 0 | E7: =+IF(C5="","",C7/D7)
A9: 4.2 | B9: Comprensión de las necesidades y expectativas de las partes interesadas
A10: =1+A6 -> 3 | B10: la organización determina las partes interesadas que son pertinentes al SGA | D10: =+IF(C10="","",+IF(C10=0,"No Cumple",+IF(C10=1,"Cumple Parcial",+IF(C10=2,"Cumple Completo",+IF(C10="N","NA")))))
A11: =1+A10 -> 4 | B11: La organización determina las necesidades y expectativas (es decir, requisitos) de estas partes interesadas | D11: =+IF(C11="","",+IF(C11=0,"No Cumple",+IF(C11=1,"Cumple Parcial",+IF(C11=2,"Cumple Completo",+IF(C11="N","NA")))))
A12: =1+A11 -> 5 | B12: La organización determina cuáles de estas necesidades y expectativas se convierten en requisitos legales y otros requisitos | D12: =+IF(C12="","",+IF(C12=0,"No Cumple",+IF(C12=1,"Cumple Parcial",+IF(C12=2,"Cumple Completo",+IF(C12="N","NA")))))
C13: =SUM(C10:C12) -> 0 | D13: =+COUNT(C10:C12)*2 -> 0 | E13: =+IF(C10="","",C13/D13)
A15: 4.3 | B15: Determinación del alcance del sistema de gestión ambiental
A16: =1+A12 -> 6 | B16: La organización determina los límites y la aplicabilidad del SGA para establecer su alcance. | D16: =+IF(C16="","",+IF(C16=0,"No Cumple",+IF(C16=1,"Cumple Parcial",+IF(C16=2,"Cumple Completo",+IF(C16="N","NA")))))
A17: =1+A16 -> 7 | B17: Al determinar el alcance, la organización considera: | D17: =+IF(C17="","",+IF(C17=0,"No Cumple",+IF(C17=1,"Cumple Parcial",+IF(C17=2,"Cumple Completo",+IF(C17="N","NA")))))
A18: =1+A17 -> 8 | B18: a) Las cuestiones externas e internas a que se hace referencia en el apartado 4.1 | D18: =+IF(C18="","",+IF(C18=0,"No Cumple",+IF(C18=1,"Cumple Parcial",+IF(C18=2,"Cumple Completo",+IF(C18="N","NA")))))
A19: =1+A18 -> 9 | B19: b) Los requisitos de las partes interesadas pertinentes, referido en el apartado 4.2 | D19: =+IF(C19="","",+IF(C19=0,"No Cumple",+IF(C19=1,"Cumple Parcial",+IF(C19=2,"Cumple Completo",+IF(C19="N","NA")))))
A20: =1+A19 -> 10 | B20: c) Las unidades, funciones y límites físicos de la organización | D20: =+IF(C20="","",+IF(C20=0,"No Cumple",+IF(C20=1,"Cumple Parcial",+IF(C20=2,"Cumple Completo",+IF(C20="N","NA")))))
A21: =1+A20 -> 11 | B21: d) sus actividades, productos y servicios | D21: =+IF(C21="","",+IF(C21=0,"No Cumple",+IF(C21=1,"Cumple Parcial",+IF(C21=2,"Cumple Completo",+IF(C21="N","NA")))))
A22: =1+A21 -> 12 | B22: e) su autoridad y capacidad para ejercer control e influencia | D22: =+IF(C22="","",+IF(C22=0,"No Cumple",+IF(C22=1,"Cumple Parcial",+IF(C22=2,"Cumple Completo",+IF(C22="N","NA")))))
A23: =1+A22 -> 13 | B23: Una vez que se defina el alcance, se deben incluir en el SGA todas las actividades, productos y servicios de la organización que estén dentro de este alcance. | D23: =+IF(C23="","",+IF(C23=0,"No Cumple",+IF(C23=1,"Cumple Parcial",+IF(C23=2,"Cumple Completo",+IF(C23="N","NA")))))
A24: =1+A23 -> 14 | B24: La organización dispone y mantiene información documentada y debe estar disponible para las partes interesadas. | D24: =+IF(C24="","",+IF(C24=0,"No Cumple",+IF(C24=1,"Cumple Parcial",+IF(C24=2,"Cumple Completo",+IF(C24="N","NA")))))
C25: =SUM(C16:C24) -> 0 | D25: =+COUNT(C16:C24)*2 -> 0 | E25: =+IF(C16="","",C25/D25)
A27: 4.4 | B27: Sistema de gestión de la calidad y sus procesos
A28: =1+A24 -> 15 | B28: La organización debe establecer, implementar, mantener y mejorar continuamente un SGA, incluidos los procesos y sus interacciones, de acuerdo a esta norma internacional, y debe: | D28: =+IF(C28="","",+IF(C28=0,"No Cumple",+IF(C28=1,"Cumple Parcial",+IF(C28=2,"Cumple Completo",+IF(C28="N","NA")))))
A29: =1+A28 -> 16 | B29: a) Determinar las entradas requeridas y las salidas esperadas de estos procesos | D29: =+IF(C29="","",+IF(C29=0,"No Cumple",+IF(C29=1,"Cumple Parcial",+IF(C29=2,"Cumple Completo",+IF(C29="N","NA")))))
A30: =1+A29 -> 17 | B30: b) Determinar la secuencia e interacción de los procesos | D30: =+IF(C30="","",+IF(C30=0,"No Cumple",+IF(C30=1,"Cumple Parcial",+IF(C30=2,"Cumple Completo",+IF(C30="N","NA")))))
A31: =1+A30 -> 18 | B31: c) Determinar y aplicar los criterios y los métodos (seguimiento, medición, indicadores del desempeño) | D31: =+IF(C31="","",+IF(C31=0,"No Cumple",+IF(C31=1,"Cumple Parcial",+IF(C31=2,"Cumple Completo",+IF(C31="N","NA")))))
A32: =1+A31 -> 19 | B32: d) Determinar los recursos necesarios para estos procesos y asegurarse de su disponibilidad | D32: =+IF(C32="","",+IF(C32=0,"No Cumple",+IF(C32=1,"Cumple Parcial",+IF(C32=2,"Cumple Completo",+IF(C32="N","NA")))))
A33: =1+A32 -> 20 | B33: e) Asignar las responsabilidades y autoridades para estos procesos | D33: =+IF(C33="","",+IF(C33=0,"No Cumple",+IF(C33=1,"Cumple Parcial",+IF(C33=2,"Cumple Completo",+IF(C33="N","NA")))))
A34: =1+A33 -> 21 | B34: f) Abordar los riesgos y oportunidades determinados de acuerdo con los requisitos del apartado 6.1 | D34: =+IF(C34="","",+IF(C34=0,"No Cumple",+IF(C34=1,"Cumple Parcial",+IF(C34=2,"Cumple Completo",+IF(C34="N","NA")))))
A35: =1+A34 -> 22 | B35: Al establecer y mantener el SGA, la organización debe considerar el conocimiento obtenido en los apartados 4.1 y 4.2 | D35: =+IF(C35="","",+IF(C35=0,"No Cumple",+IF(C35=1,"Cumple Parcial",+IF(C35=2,"Cumple Completo",+IF(C35="N","NA")))))
A36: =1+A35 -> 23 | B36: h) Mejorar los procesos y el sistema de gestión ambiental | D36: =+IF(C36="","",+IF(C36=0,"No Cumple",+IF(C36=1,"Cumple Parcial",+IF(C36=2,"Cumple Completo",+IF(C36="N","NA")))))
C37: =SUM(C28:C36) -> 0 | D37: =+COUNT(C28:C36)*2 -> 0 | E37: =+IF(C28="","",C37/D37) | G37: =+IF(E7="","",+AVERAGE(E7,E13,E25,E37))
A39: 5.1 | B39: Liderazgo y compromiso
A40: 5.1.1 | B40: Generalidades
A41: =1+A36 -> 24 | B41: La alta dirección debe demostrar liderazgo y compromiso con respecto al SGA: | D41: =+IF(C41="","",+IF(C41=0,"No Cumple",+IF(C41=1,"Cumple Parcial",+IF(C41=2,"Cumple Completo",+IF(C41="N","NA")))))
A42: =1+A41 -> 25 | B42: a) asumiendo la responsabilidad y obligación de rendir cuentas con relación a la eficacia del SGA | D42: =+IF(C42="","",+IF(C42=0,"No Cumple",+IF(C42=1,"Cumple Parcial",+IF(C42=2,"Cumple Completo",+IF(C42="N","NA")))))
A43: =1+A42 -> 26 | B43: b) asegurándose de que se establezcan la política y los objetivos ambientales para el SGA, y que estos sean compatibles con el contexto y la dirección estratégica de la organización | D43: =+IF(C43="","",+IF(C43=0,"No Cumple",+IF(C43=1,"Cumple Parcial",+IF(C43=2,"Cumple Completo",+IF(C43="N","NA")))))
A44: =1+A43 -> 27 | B44: c) asegurándose de la integración de los requisitos del SGA en los procesos de negocio de la organización | D44: =+IF(C44="","",+IF(C44=0,"No Cumple",+IF(C44=1,"Cumple Parcial",+IF(C44=2,"Cumple Completo",+IF(C44="N","NA")))))
A45: =1+A44 -> 28 | B45: d) asegurándose de que los recursos necesarios para el SGA estén disponibles | D45: =+IF(C45="","",+IF(C45=0,"No Cumple",+IF(C45=1,"Cumple Parcial",+IF(C45=2,"Cumple Completo",+IF(C45="N","NA")))))
A46: =1+A45 -> 29 | B46: e) comunicando la importancia de una gestión ambiental eficaz y conforme con los requisitos del SGA | D46: =+IF(C46="","",+IF(C46=0,"No Cumple",+IF(C46=1,"Cumple Parcial",+IF(C46=2,"Cumple Completo",+IF(C46="N","NA")))))
A47: =1+A46 -> 30 | B47: f) asegurándose de que el SGA logre los resultados previstos | D47: =+IF(C47="","",+IF(C47=0,"No Cumple",+IF(C47=1,"Cumple Parcial",+IF(C47=2,"Cumple Completo",+IF(C47="N","NA")))))
A48: =1+A47 -> 31 | B48: g) comprometiendo, dirigiendo y apoyando a las personas, para contribuir a la eficacia del SGA | D48: =+IF(C48="","",+IF(C48=0,"No Cumple",+IF(C48=1,"Cumple Parcial",+IF(C48=2,"Cumple Completo",+IF(C48="N","NA")))))
A49: =1+A48 -> 32 | B49: h) Promoviendo la mejora continua | D49: =+IF(C49="","",+IF(C49=0,"No Cumple",+IF(C49=1,"Cumple Parcial",+IF(C49=2,"Cumple Completo",+IF(C49="N","NA")))))
A50: =1+A49 -> 33 | B50: i) apoyando otros roles pertinentes de la dirección, para demostrar su liderazgo en la forma en la que aplique a sus áreas de responsabilidad | D50: =+IF(C50="","",+IF(C50=0,"No Cumple",+IF(C50=1,"Cumple Parcial",+IF(C50=2,"Cumple Completo",+IF(C50="N","NA")))))
C51: =SUM(C41:C50) -> 0 | D51: =+COUNT(C41:C50)*2 -> 0 | E51: =+IF(C42="","",C51/D51)
A52: 5.2 | B52: Política Ambiental
A53: =1+A50 -> 34 | B53: La alta dirección debe establecer, implementar y mantener una política ambiental que, dentro del alcance definido en el SGA: | D53: =+IF(C53="","",+IF(C53=0,"No Cumple",+IF(C53=1,"Cumple Parcial",+IF(C53=2,"Cumple Completo",+IF(C53="N","NA")))))
A54: =1+A53 -> 35 | B54: a) sea apropiada al propósito y contexto de la organización, incluida la naturaleza, magnitud e impactos ambientales de sus actividades, procesos y servicios | D54: =+IF(C54="","",+IF(C54=0,"No Cumple",+IF(C54=1,"Cumple Parcial",+IF(C54=2,"Cumple Completo",+IF(C54="N","NA")))))
A55: =1+A54 -> 36 | B55: b) proporcione un marco de referencia para el establecimiento de los objetivos ambientales | D55: =+IF(C55="","",+IF(C55=0,"No Cumple",+IF(C55=1,"Cumple Parcial",+IF(C55=2,"Cumple Completo",+IF(C55="N","NA")))))
A56: =1+A55 -> 37 | B56: c) incluya un compromiso para la protección del medio ambiente, incluida la prevención de la contaminación, y otros compromisos específicos pertinentes al contexto de la organización | D56: =+IF(C56="","",+IF(C56=0,"No Cumple",+IF(C56=1,"Cumple Parcial",+IF(C56=2,"Cumple Completo",+IF(C56="N","NA")))))
A57: =1+A56 -> 38 | B57: d) incluya un compromiso de cumplir requisitos legales y otros aplicables | D57: =+IF(C57="","",+IF(C57=0,"No Cumple",+IF(C57=1,"Cumple Parcial",+IF(C57=2,"Cumple Completo",+IF(C57="N","NA")))))
A58: =1+A57 -> 39 | B58: e) incluya un compromiso de mejora continua del SGA | D58: =+IF(C58="","",+IF(C58=0,"No Cumple",+IF(C58=1,"Cumple Parcial",+IF(C58=2,"Cumple Completo",+IF(C58="N","NA")))))
A59: =1+A58 -> 40 | B59: La política de calidad debe: | D59: =+IF(C59="","",+IF(C59=0,"No Cumple",+IF(C59=1,"Cumple Parcial",+IF(C59=2,"Cumple Completo",+IF(C59="N","NA")))))
A60: =1+A59 -> 41 | B60: a) estar disponible y mantenerse como información documentada | D60: =+IF(C60="","",+IF(C60=0,"No Cumple",+IF(C60=1,"Cumple Parcial",+IF(C60=2,"Cumple Completo",+IF(C60="N","NA")))))
A61: =1+A60 -> 42 | B61: b) comunicarse, entenderse y aplicarse dentro de la organización | D61: =+IF(C61="","",+IF(C61=0,"No Cumple",+IF(C61=1,"Cumple Parcial",+IF(C61=2,"Cumple Completo",+IF(C61="N","NA")))))
A62: =1+A61 -> 43 | B62: estar disponible para las partes interesadas pertinentes, según corresponda | D62: =+IF(C62="","",+IF(C62=0,"No Cumple",+IF(C62=1,"Cumple Parcial",+IF(C62=2,"Cumple Completo",+IF(C62="N","NA")))))
C63: =SUM(C53:C62) -> 0 | D63: =+COUNT(C53:C62)*2 -> 0 | E63: =+IF(C53="","",C63/D63)
A64: 5.3 | B64: Roles, responsabilidad y autoridades en la organización
A65: =1+A62 -> 44 | B65: La alta dirección debe asegurarse de que las responsabilidades y autoridades para los roles pertinentes se asignen, se comuniquen y se entienden en toda la organización. | D65: =+IF(C65="","",+IF(C65=0,"No Cumple",+IF(C65=1,"Cumple Parcial",+IF(C65=2,"Cumple Completo",+IF(C65="N","NA")))))
A66: =1+A65 -> 45 | B66: La alta dirección debe asignar la responsabilidad y autoridad para: | D66: =+IF(C66="","",+IF(C66=0,"No Cumple",+IF(C66=1,"Cumple Parcial",+IF(C66=2,"Cumple Completo",+IF(C66="N","NA")))))
A67: =1+A66 -> 46 | B67: a) asegurarse de que el SGA es conforme con los requisitos de esta Norma Internacional | D67: =+IF(C67="","",+IF(C67=0,"No Cumple",+IF(C67=1,"Cumple Parcial",+IF(C67=2,"Cumple Completo",+IF(C67="N","NA")))))
A68: =1+A67 -> 47 | B68: b) informar a la alta dirección sobre el desempeño del SGA, incluyendo su desempeño ambiental | D68: =+IF(C68="","",+IF(C68=0,"No Cumple",+IF(C68=1,"Cumple Parcial",+IF(C68=2,"Cumple Completo",+IF(C68="N","NA")))))
C69: =SUM(C65:C68) -> 0 | D69: =+COUNT(C65:C68)*2 -> 0 | E69: =+IF(C65="","",C69/D69) | G69: =+IF(E51="","",+AVERAGE(E51,E63,E69))
A71: 6 | B71: PLANIFICACIÓN
A72: 6.1 | B72: Acciones para abordar riesgos y oportunidades
A73: 6.1.1 | B73: Generalidades
A74: =1+A68 -> 48 | B74: La organización debe establecer, implementar y mantener los procesos necesarios para cumplir los requisitos de los apartados 6.1.1 a 6.1.4. | D74: =+IF(C74="","",+IF(C74=0,"No Cumple",+IF(C74=1,"Cumple Parcial",+IF(C74=2,"Cumple Completo",+IF(C74="N","NA")))))
A75: =1+A74 -> 49 | B75: Al planificar el SGA, la organización debe considerar:
A76: =1+A75 -> 50 | B76: a) las cuestiones referidas en el apartado 4.1 | D76: =+IF(C76="","",+IF(C76=0,"No Cumple",+IF(C76=1,"Cumple Parcial",+IF(C76=2,"Cumple Completo",+IF(C76="N","NA")))))
A77: =1+A76 -> 51 | B77: b) los requisitos referidos en el apartado 4.2 | D77: =+IF(C77="","",+IF(C77=0,"No Cumple",+IF(C77=1,"Cumple Parcial",+IF(C77=2,"Cumple Completo",+IF(C77="N","NA")))))
A78: =1+A77 -> 52 | B78: c) el alcance de su sistema de gestión ambiental | D78: =+IF(C78="","",+IF(C78=0,"No Cumple",+IF(C78=1,"Cumple Parcial",+IF(C78=2,"Cumple Completo",+IF(C78="N","NA")))))
A79: =1+A78 -> 53 | B79: y determinar los riesgos y oportunidades relacionados con sus: | D79: =+IF(C79="","",+IF(C79=0,"No Cumple",+IF(C79=1,"Cumple Parcial",+IF(C79=2,"Cumple Completo",+IF(C79="N","NA")))))
A80: =1+A79 -> 54 | B80: aspectos ambientales (véase 6.1.2) | D80: =+IF(C80="","",+IF(C80=0,"No Cumple",+IF(C80=1,"Cumple Parcial",+IF(C80=2,"Cumple Completo",+IF(C80="N","NA")))))
A81: =1+A80 -> 55 | B81: requisitos legales y otros requisitos (véase 6.1.3) | D81: =+IF(C81="","",+IF(C81=0,"No Cumple",+IF(C81=1,"Cumple Parcial",+IF(C81=2,"Cumple Completo",+IF(C81="N","NA")))))
A82: =1+A81 -> 56 | B82: y otras cuestiones y requisitos identificados en los apartados 4.1 y 4.2 | D82: =+IF(C82="","",+IF(C82=0,"No Cumple",+IF(C82=1,"Cumple Parcial",+IF(C82=2,"Cumple Completo",+IF(C82="N","NA")))))
A83: =1+A82 -> 57 | B83: que necesitan abordarse para: | D83: =+IF(C83="","",+IF(C83=0,"No Cumple",+IF(C83=1,"Cumple Parcial",+IF(C83=2,"Cumple Completo",+IF(C83="N","NA")))))
A84: =1+A83 -> 58 | B84: asegurar que el SGA puede lograr sus resultados previstos | D84: =+IF(C84="","",+IF(C84=0,"No Cumple",+IF(C84=1,"Cumple Parcial",+IF(C84=2,"Cumple Completo",+IF(C84="N","NA")))))
A85: =1+A84 -> 59 | B85: prevenir o reducir los efectos no deseados, incluida la posibilidad de que condiciones ambientales externas afectan a la organización. | D85: =+IF(C85="","",+IF(C85=0,"No Cumple",+IF(C85=1,"Cumple Parcial",+IF(C85=2,"Cumple Completo",+IF(C85="N","NA")))))
A86: =1+A85 -> 60 | B86: lograr la mejora continua | D86: =+IF(C86="","",+IF(C86=0,"No Cumple",+IF(C86=1,"Cumple Parcial",+IF(C86=2,"Cumple Completo",+IF(C86="N","NA")))))
A87: =1+A86 -> 61 | B87: Dentro del alcance del SGA, la organización debe determinar las situaciones de emergencia potenciales, incluidas las que pueden tener un impacto ambiental. | D87: =+IF(C87="","",+IF(C87=0,"No Cumple",+IF(C87=1,"Cumple Parcial",+IF(C87=2,"Cumple Completo",+IF(C87="N","NA")))))
... A90: =1+A89 -> 64 | B90: procesos necesarios especificados desde el apartado 6.1.1 al apartado 6.1.4, en la medida necesaria para tener confianza de que se llevan a cabo de la manera planificada. | D90: =+IF(C90="","",+IF(C90=0,"No Cumple",+IF(C90=1,"Cumple Parcial",+IF(C90=2,"Cumple Completo",+IF(C90="N","NA")))))
C91: =SUM(C74:C90) -> 0 | D91: =+COUNT(C74:C90)*2 -> 0 | E91: =+IF(C74="","",C91/D91)
A92: 6.1.2 | B92: Aspectos ambientales
A93: =1+A90 -> 65 | B93: Dentro del alcance definido del SGA, la organización debe determinar los aspectos ambientales de sus actividades, productos y servicios que puede controlar y de aquellos en los que puede influir, y sus impactos ambientales asociados, desde una perspectiva de ciclo de vida. | D93: =+IF(C93="","",+IF(C93=0,"No Cumple",+IF(C93=1,"Cumple Parcial",+IF(C93=2,"Cumple Completo",+IF(C93="N","NA")))))
A94: =1+A93 -> 66 | B94: a) los cambios, incluidos los desarrollos nuevos o planificados, y las actividades, productos y servicios nuevos o modificados. | D94: =+IF(C94="","",+IF(C94=0,"No Cumple",+IF(C94=1,"Cumple Parcial",+IF(C94=2,"Cumple Completo",+IF(C94="N","NA")))))
A95: =1+A94 -> 67 | B95: b) las condiciones anormales y las situaciones de emergencia razonablemente previsibles. | D95: =+IF(C95="","",+IF(C95=0,"No Cumple",+IF(C95=1,"Cumple Parcial",+IF(C95=2,"Cumple Completo",+IF(C95="N","NA")))))
A96: =1+A95 -> 68 | B96: La organización debe determinar aquellos aspectos que tengan o puedan tener un impacto ambiental significativo, es decir, los aspectos ambientales significativos, mediante el uso de criterios establecidos. | D96: =+IF(C96="","",+IF(C96=0,"No Cumple",+IF(C96=1,"Cumple Parcial",+IF(C96=2,"Cumple Completo",+IF(C96="N","NA")))))
A97: =1+A96 -> 69 | B97: La organización debe comunicar sus aspectos ambientales significativos entre los diferentes niveles y funciones de la organización, según corresponda. | D97: =+IF(C97="","",+IF(C97=0,"No Cumple",+IF(C97=1,"Cumple Parcial",+IF(C97=2,"Cumple Completo",+IF(C97="N","NA")))))
A98: =1+A97 -> 70 | B98: La organización debe mantener información documentada de sus: | D98: =+IF(C98="","",+IF(C98=0,"No Cumple",+IF(C98=1,"Cumple Parcial",+IF(C98=2,"Cumple Completo",+IF(C98="N","NA")))))
A99: =1+A98 -> 71 | B99: · Aspectos ambientales e impactos ambientales asociados | D99: =+IF(C99="","",+IF(C99=0,"No Cumple",+IF(C99=1,"Cumple Parcial",+IF(C99=2,"Cumple Completo",+IF(C99="N","NA")))))
A100: =1+A99 -> 72 | B100: · Criterios usados para determinar sus aspectos ambientales significativos | D100: =+IF(C100="","",+IF(C100=0,"No Cumple",+IF(C100=1,"Cumple Parcial",+IF(C100=2,"Cumple Completo",+IF(C100="N","NA")))))
A101: =1+A100 -> 73 | B101: · Aspectos ambientales significativos. | D101: =+IF(C101="","",+IF(C101=0,"No Cumple",+IF(C101=1,"Cumple Parcial",+IF(C101=2,"Cumple Completo",+IF(C101="N","NA")))))
C102: =SUM(C93:C101) -> 0 | D102: =+COUNT(C93:C101)*2 -> 0 | E102: =+IF(C93="","",C102/D102)
A103: 6.1.3 | B103: Requisitos legales y otros requisitos
A104: =1+A101 -> 74 | B104: La organización debe: | D104: =+IF(C104="","",+IF(C104=0,"No Cumple",+IF(C104=1,"Cumple Parcial",+IF(C104=2,"Cumple Completo",+IF(C104="N","NA")))))
A105: =1+A104 -> 75 | B105: a) Determinar y tener acceso a los requisitos legales y otros requisitos relacionados con sus aspectos ambientales | D105: =+IF(C105="","",+IF(C105=0,"No Cumple",+IF(C105=1,"Cumple Parcial",+IF(C105=2,"Cumple Completo",+IF(C105="N","NA")))))
A106: =1+A105 -> 76 | B106: b) Determinar cómo estos requisitos legales y otros requisitos se aplican a la organiación. | D106: =+IF(C106="","",+IF(C106=0,"No Cumple",+IF(C106=1,"Cumple Parcial",+IF(C106=2,"Cumple Completo",+IF(C106="N","NA")))))
A107: =1+A106 -> 77 | B107: c) Tener en cuenta estos requisitos legales y otros requisitos cuando se establezca, implemente, mantenga y mejore continuamente su SGA. | D107: =+IF(C107="","",+IF(C107=0,"No Cumple",+IF(C107=1,"Cumple Parcial",+IF(C107=2,"Cumple Completo",+IF(C107="N","NA")))))
A108: =1+A107 -> 78 | B108: La organización debe mantener información documentada de sus requisitos legales y otros requisitos. | D108: =+IF(C108="","",+IF(C108=0,"No Cumple",+IF(C108=1,"Cumple Parcial",+IF(C108=2,"Cumple Completo",+IF(C108="N","NA")))))
...

Sheet SST
B1: ANÁLISIS DE BRECHAS (GAP ANALYSIS) SG-SST | D1: ÍNDICE
A2: 4. | B2: CONTEXTO DE LA ORGANIZACIÓN
A3: 4.1 | B3: Comprensión de la organización y su contexto
A4: 1 | B4: La organización debe determinar las cuestiones externas e internas que son pertinentes para su propósito y que afecta a su capacidad para alcanzar los resultados previstos de su sistema de gestión de la SST. | D4: =+IF(C4="","",+IF(C4=0,"No Cumple",+IF(C4=1,"Cumple Parcial",+IF(C4=2,"Cumple Completo",+IF(C4="N","NA")))))
A5: =1+A4 -> 2 | B5: Ejemplos de factores del contexto externo que pueden obtenerse a través del análisis de PESTAL incluye: 1. Grupos de presión y sindicatos de trabajadores; 2. Aseguradores y stakeholder Vistas; 3. Las condiciones económicas; 4. Las expectativas sociales y prioridades politicas; 5. La legislación y la observancia; 6. Las agencias nacionales/internacionales. Ejemplos de de contexto interno que pueden obtenerse a través del análisis DOFA (SWOT) incluye: 1. Estructura, responsabilidades, competencias y control; 2. Nuevos productos, asuntos contractuales, cooperación y comunicaciones. | D5: =+IF(C5="","",+IF(C5=0,"No Cumple",+IF(C5=1,"Cumple Parcial",+IF(C5=2,"Cumple Completo",+IF(C5="N","NA")))))
C6: =SUM(C3:C5) -> 0 | D6: =+COUNT(C3:C5)*2 -> 0 | E6: =+IF(C4="","",C6/D6)
A7: 4.2 | B7: Comprensión de las necesidades y expectativas de los trabajadores y otras partes interesadas. La organización debe determinar:
A8: =1+A5 -> 3 | B8: a) Las partes interesadas, además de los trabajadores, que son pertinentes al SG-SST | D8: =+IF(C8="","",+IF(C8=0,"No Cumple",+IF(C8=1,"Cumple Parcial",+IF(C8=2,"Cumple Completo",+IF(C8="N","NA")))))
A9: =1+A8 -> 4 | B9: b) las necesidades y expectativas pertinentes (es decir, los requisitos) de los trabajadores y de otras partes interesadas | D9: =+IF(C9="","",+IF(C9=0,"No Cumple",+IF(C9=1,"Cumple Parcial",+IF(C9=2,"Cumple Completo",+IF(C9="N","NA")))))
A10: =1+A9 -> 5 | B10: c) cuáles de las necesidades y expectativas son o podrían convertirse, en requisitos legales y otros requisitos. | D10: =+IF(C10="","",+IF(C10=0,"No Cumple",+IF(C10=1,"Cumple Parcial",+IF(C10=2,"Cumple Completo",+IF(C10="N","NA")))))
A11: =1+A10 -> 6 | B11: ¿Quién podría afectar o verse afectado por sus actividades y cuáles podrían ser sus intereses relevantes y significativos? ¿Ha tenido en cuenta sus necesidades dentro sistema de gestión de la SST ? 1. Necesidades y expectaciones tanto de gestión y trabajadores no directivos y representantes de los trabajadores (donde existan); 2. Afectan al SG-SST o que se perciben afectados por el SG-SST (a. 4.2); 3. Trabajador y representantes apropiados de los trabajadores; 4. Requisitos legal y regulatorios 5. Otras organizaciones relacionados o perteneciente a un grupo 6. Proveedores, contratistas y subcontratistas; 7. Las organizaciones de trabajadores (sindicatos) y las organizaciones de empleadores 8. Propietarios, accionistas, clientes, visitantes, comunidad local, vecinos, público en general; 9. Salud ocupacional y organizaciones de seguridad; profesionales de seguridad y salud ocupacional (p. ej., médicos, enfermeras). | D11: =+IF(C11="","",+IF(C11=0,"No Cumple",+IF(C11=1,"Cumple Parcial",+IF(C11=2,"Cumple Completo",+IF(C11="N","NA")))))
C12: =SUM(C8:C11) -> 0 | D12: =+COUNT(C8:C11)*2 -> 0 | E12: =+IF(C8="","",C12/D12)
A13: 4.3 | B13: Determinación del alcance del SG-SST
A14: =1+A11 -> 7 | B14: La organización debe determinar los límites y la aplicabilidad del SG-SST para establecer su alcance. | D14: =+IF(C14="","",+IF(C14=0,"No Cumple",+IF(C14=1,"Cumple Parcial",+IF(C14=2,"Cumple Completo",+IF(C14="N","NA")))))
A15: =1+A14 -> 8 | B15: Cuando se determine su alcance, la organización debe: a) Considerar las cuestiones externas e internas indicadas en el apartado 4.1 | D15: =+IF(C15="","",+IF(C15=0,"No Cumple",+IF(C15=1,"Cumple Parcial",+IF(C15=2,"Cumple Completo",+IF(C15="N","NA")))))
A16: =1+A15 -> 9 | B16: b) Tener en cuenta los requisitos indicados en el apartado 4.2 | D16: =+IF(C16="","",+IF(C16=0,"No Cumple",+IF(C16=1,"Cumple Parcial",+IF(C16=2,"Cumple Completo",+IF(C16="N","NA")))))
A17: =1+A16 -> 10 | B17: c) tener en cuenta las actividades relacionadas con el trabajo, planificadas o relacionadas | D17: =+IF(C17="","",+IF(C17=0,"No Cumple",+IF(C17=1,"Cumple Parcial",+IF(C17=2,"Cumple Completo",+IF(C17="N","NA")))))
A18: =1+A17 -> 11 | B18: El SG-SST debe incluir las actividades, los productos y los servicios bajo el control o la influencia de la organización que pueden tener impacto en el desempeño de la SST de la organización. | D18: =+IF(C18="","",+IF(C18=0,"No Cumple",+IF(C18=1,"Cumple Parcial",+IF(C18=2,"Cumple Completo",+IF(C18="N","NA")))))
A19: =1+A18 -> 12 | B19: El alcance debe estar disponible como información documentada. | D19: =+IF(C19="","",+IF(C19=0,"No Cumple",+IF(C19=1,"Cumple Parcial",+IF(C19=2,"Cumple Completo",+IF(C19="N","NA")))))
A20: =1+A19 -> 13 | B20: Asegúrese de que la aplicación del alcance sea relevante para: 1. Las cuestiones externas e internas mencionadas en el 4,1; 2. Requisitos contemplados en el 4,2; 3. el tipos de actividades relacionadas con el trabajo realizadas. Cualquier cambio en el alcance debe estar sujeto a los requisitos de la norma y sujeta a auditoría mediante la evaluación de la conformidad. | D20: =+IF(C20="","",+IF(C20=0,"No Cumple",+IF(C20=1,"Cumple Parcial",+IF(C20=2,"Cumple Completo",+IF(C20="N","NA")))))
C21: =SUM(C14:C16) -> 0 | D21: =+COUNT(C14:C16)*2 -> 0 | E21: =+IF(C14="","",C21/D21)
A22: 4.4 | B22: Sistema de gestión de la SST
A23: =1+A20 -> 14 | B23: La organización debe establecer, implementar, mantener y mejorar continuamente un SG-SST, incluidos los procesos necesarios y sus interacciones, de acuerdo con los requisitos de este documento. | D23: =+IF(C23="","",+IF(C23=0,"No Cumple",+IF(C23=1,"Cumple Parcial",+IF(C23=2,"Cumple Completo",+IF(C23="N","NA")))))
A24: =1+A23 -> 15 | B24: Se proporciona evidencia útil para demostrar los procesos que sustan las actividades del SG-SST. Contar con una matriz de procesos facilita la planificación, porque proporciona interacción con los requisitos de otras cláusulas, incluidas las relacionadas con el riesgo, la planificación, los recursos y el monitoreo y la medición de los resultados de los sistema de gestión. La matriz de proceso puede ser un elemento útil para presentar en la auditoría. | D24: =+IF(C24="","",+IF(C24=0,"No Cumple",+IF(C24=1,"Cumple Parcial",+IF(C24=2,"Cumple Completo",+IF(C24="N","NA")))))
C25: =SUM(C23:C24) -> 0 | D25: =+COUNT(C23:C24)*2 -> 0 | E25: =+IF(C23="","",C25/D25) | G25: =+IF(E6="","",+AVERAGE(E6,E12,E25))
A26: 5 | B26: LIDERAZGO Y PARTICIPACIÓN DE LOS TRABAJADORES
A27: 5.1 | B27: Liderazgo y compromiso La lata dirección debe demostrar liderazgo y compromiso con respecto al SG-SST:
A28: =1+A24 -> 16 | B28: a) Asumiendo la total responsabilidad y rendición de cuentas para la prevención de las lesiones y el deterioro de la salud relacionados con el trabajo, así como la provisión de actividades y lugares de trabajo seguros y saludables | D28: =+IF(C28="","",+IF(C28=0,"No Cumple",+IF(C28=1,"Cumple Parcial",+IF(C28=2,"Cumple Completo",+IF(C28="N","NA")))))
A29: =1+A28 -> 17 | B29: b) asegurándose de que se establezcan la política de la SST y los objetivos relacionados con la SST y sean compatibles con la dirección estratégica de la organización. | D29: =+IF(C29="","",+IF(C29=0,"No Cumple",+IF(C29=1,"Cumple Parcial",+IF(C29=2,"Cumple Completo",+IF(C29="N","NA")))))
A30: =1+A29 -> 18 | B30: c) asegurándose de la integración de los requisitos del SG-SST en los procesos de negocio de la organización. | D30: =+IF(C30="","",+IF(C30=0,"No Cumple",+IF(C30=1,"Cumple Parcial",+IF(C30=2,"Cumple Completo",+IF(C30="N","NA")))))
A31: =1+A30 -> 19 | B31: d) asegurándose de que los recursos necesarios para establecer, implementar, mantener y mejorar el SG-SST estén disponibles. | D31: =+IF(C31="","",+IF(C31=0,"No Cumple",+IF(C31=1,"Cumple Parcial",+IF(C31=2,"Cumple Completo",+IF(C31="N","NA")))))
A32: =1+A31 -> 20 | B32: e) comunicando la importancia de una gestión de SST eficaz y conforme con los requisitos del SG-SST. | D32: =+IF(C32="","",+IF(C32=0,"No Cumple",+IF(C32=1,"Cumple Parcial",+IF(C32=2,"Cumple Completo",+IF(C32="N","NA")))))
A33: =1+A32 -> 21 | B33: f) asegurándose de que el SG-SST alcance los resultados previstos. | D33: =+IF(C33="","",+IF(C33=0,"No Cumple",+IF(C33=1,"Cumple Parcial",+IF(C33=2,"Cumple Completo",+IF(C33="N","NA")))))
A34: =1+A33 -> 22 | B34: g) dirigiendo y apoyando a las personas, para contribuir a la eficacia del SG-SST. | D34: =+IF(C34="","",+IF(C34=0,"No Cumple",+IF(C34=1,"Cumple Parcial",+IF(C34=2,"Cumple Completo",+IF(C34="N","NA")))))
A35: =1+A34 -> 23 | B35: h) asegurando y promoviendo la mejora continua. | D35: =+IF(C35="","",+IF(C35=0,"No Cumple",+IF(C35=1,"Cumple Parcial",+IF(C35=2,"Cumple Completo",+IF(C35="N","NA")))))
A36: =1+A35 -> 24 | B36: i) apoyando otros roles pertinentes de la dirección, para demostrar su liderazgo aplicado a sus áreas de responsabilidad. | D36: =+IF(C36="","",+IF(C36=0,"No Cumple",+IF(C36=1,"Cumple Parcial",+IF(C36=2,"Cumple Completo",+IF(C36="N","NA")))))
A37: =1+A36 -> 25 | B37: j) desarrollando, liderando y promoviendo una cultura en la organización que apoye los resultados previstos del SG-SST. | D37: =+IF(C37="","",+IF(C37=0,"No Cumple",+IF(C37=1,"Cumple Parcial",+IF(C37=2,"Cumple Completo",+IF(C37="N","NA")))))
A38: =1+A37 -> 26 | B38: k) protegiendo a los trabajadores de represalias al informar de incidentes, peligros, riesgos y oportunidades. | D38: =+IF(C38="","",+IF(C38=0,"No Cumple",+IF(C38=1,"Cumple Parcial",+IF(C38=2,"Cumple Completo",+IF(C38="N","NA")))))
A39: =1+A38 -> 27 | B39: l) asegurándose de que la organización establezca e implemente procesos para la consulta y la participación de los trabajadores. | D39: =+IF(C39="","",+IF(C39=0,"No Cumple",+IF(C39=1,"Cumple Parcial",+IF(C39=2,"Cumple Completo",+IF(C39="N","NA")))))
A40: =1+A39 -> 28 | B40: m) apoyando el establecimiento y funcionamiento de comités de seguridad y salud (véase 5.4-e) | D40: =+IF(C40="","",+IF(C40=0,"No Cumple",+IF(C40=1,"Cumple Parcial",+IF(C40=2,"Cumple Completo",+IF(C40="N","NA")))))
A41: =1+A40 -> 29 | B41: La alta dirección ha asumido el liderazgo y compromiso, en lugar de delegar a alguien más abajo en su organización. Los trabajadores están involucrados directamente para proteger, mejorar el rendimiento y apoyar el SG-SST. | D41: =+IF(C41="","",+IF(C41=0,"No Cumple",+IF(C41=1,"Cumple Parcial",+IF(C41=2,"Cumple Completo",+IF(C41="N","NA")))))
C42: =SUM(C28:C41) -> 0 | D42: =+COUNT(C28:C41)*2 -> 0 | E42: =+IF(C28="","",C42/D42)
A43: 5.2 | B43: Política de la SST
A44: =1+A41 -> 30 | B44: La alta dirección debe establecer, implemenar y mantener una política de la SST que: a) incluya un compromiso para proporcionar condiciones de trabajo seguras y saludables para la prevención de lesiones y deterioro de la salud relacionados con el trabajo y que sea apropiada al propósito, tamaño y contexto de la organización y a la naturaleza específica de sus riesgos para la SST y sus oportunidades para la SST | D44: =+IF(C44="","",+IF(C44=0,"No Cumple",+IF(C44=1,"Cumple Parcial",+IF(C44=2,"Cumple Completo",+IF(C44="N","NA")))))
A45: =1+A44 -> 31 | B45: b) proporcione un marco de referencia para el establecimiento de los objetivos de la SST | D45: =+IF(C45="","",+IF(C45=0,"No Cumple",+IF(C45=1,"Cumple Parcial",+IF(C45=2,"Cumple Completo",+IF(C45="N","NA")))))
A46: =1+A45 -> 32 | B46: c) incluya un compromiso para cumplir requisitos legales y otros requisitos | D46: =+IF(C46="","",+IF(C46=0,"No Cumple",+IF(C46=1,"Cumple Parcial",+IF(C46=2,"Cumple Completo",+IF(C46="N","NA")))))
A47: =1+A46 -> 33 | B47: d) incluya un compromiso de eliminar peligros y reducir los riesgos para la SST | D47: =+IF(C47="","",+IF(C47=0,"No Cumple",+IF(C47=1,"Cumple Parcial",+IF(C47=2,"Cumple Completo",+IF(C47="N","NA")))))
A48: =1+A47 -> 34 | B48: e) incluya un compromiso para la mejora continua del SG-SST | D48: =+IF(C48="","",+IF(C48=0,"No Cumple",+IF(C48=1,"Cumple Parcial",+IF(C48=2,"Cumple Completo",+IF(C48="N","NA")))))
A49: =1+A48 -> 35 | B49: f) Incluya un compromiso para la consulta y la participación de los trabajadores, y cuando existan, de los representantes de los trabajadores | D49: =+IF(C49="","",+IF(C49=0,"No Cumple",+IF(C49=1,"Cumple Parcial",+IF(C49=2,"Cumple Completo",+IF(C49="N","NA")))))
A50: =1+A49 -> 36 | B50: La política de la SST debe: · estar disponible como información documentada · comunicarse dentro de la organización · estar disponible para las partes interesadas, según sea apropiado · ser pertinente y apropiada | D50: =+IF(C50="","",+IF(C50=0,"No Cumple",+IF(C50=1,"Cumple Parcial",+IF(C50=2,"Cumple Completo",+IF(C50="N","NA")))))
A51: =1+A50 -> 37 | B51: Se presta más atención a la comunicación y participación de los trabajadores, en toda la organización. La organización deben comprometerse a "satisfacer" los requisitos legales y de otro tipo y deben aplicar la jerarquía de los controles a los riesgos de la SST. La política debe estar disponible como información documentada. Verificar que la declaración de política enfatiza la comunicación y la participación de los trabajadores, en toda la organización. Debe haber un compromiso explícito con la jerarquía de controles a los riesgos de la SST. | D51: =+IF(C51="","",+IF(C51=0,"No Cumple",+IF(C51=1,"Cumple Parcial",+IF(C51=2,"Cumple Completo",+IF(C51="N","NA")))))
C52: =SUM(C44:C51) -> 0 | D52: =+COUNT(C44:C51)*2 -> 0 | E52: =+IF(C44="","",C52/D52)
A53: 5.3 | B53: Roles, responsabilidades y autoridades en la organización
A54: =1+A51 -> 38 | B54: La alta dirección debe asegurarse de que las responsabilidades y autoridades para los roles pertinentes dentro del SG-SST se asignen y comuniquen a todos los niveles dentro de la organización, y se mantengan como información documentada. Los trabajadores en cada nivel de la organización deben asumir la responsabilidad de aquellos aspectos del SG-SST sobre los que tengan control. | D54: =+IF(C54="","",+IF(C54=0,"No Cumple",+IF(C54=1,"Cumple Parcial",+IF(C54=2,"Cumple Completo",+IF(C54="N","NA")))))
A55: =1+A54 -> 39 | B55: La alta dirección debe asignar responsabilidad y autoridad para: a) asegurarse de que el SG-SST es conforme con los requisitos de este documento | D55: =+IF(C55="","",+IF(C55=0,"No Cumple",+IF(C55=1,"Cumple Parcial",+IF(C55=2,"Cumple Completo",+IF(C55="N","NA")))))
A56: =1+A55 -> 40 | B56: b) informar a la alta dirección sobre el desempeño del SG-SST | D56: =+IF(C56="","",+IF(C56=0,"No Cumple",+IF(C56=1,"Cumple Parcial",+IF(C56=2,"Cumple Completo",+IF(C56="N","NA")))))
A57: =1+A56 -> 41 | B57: Nota: Mientras que la responsbilidad y autoridad se pueden asignar, finalmente, la alta dirección es la que rinde cuentas del funcionamiento del SG-SST | D57: =+IF(C57="","",+IF(C57=0,"No Cumple",+IF(C57=1,"Cumple Parcial",+IF(C57=2,"Cumple Completo",+IF(C57="N","NA")))))
A58: =1+A57 -> 42 | B58: La alta dirección puede delegar tareas, pero no la responsabilidad. ISO 45001 requiere la implicación personal para la mejor gestión del sistema de gestión de la SST. Un organigrama tradicional sigue siendo una excelente herramienta para ilustrar las líneas de reporte, pero es imperativo que se mantenga al día y disponible como información documentada. Los auditores utilizan con frecuencia el organigrama como punto de partida para una auditoría porque puede ilustrar claramente el alcance de la Sistema de gestión de la SST. | D58: =+IF(C58="","",+IF(C58=0,"No Cumple",+IF(C58=1,"Cumple Parcial",+IF(C58=2,"Cumple Completo",+IF(C58="N","NA")))))
C59: =SUM(C54:C58) -> 0 | D59: =+COUNT(C54:C58)*2 -> 0 | E59: =+IF(C54="","",C59/D59)
A60: 5.4 | B60: Consulta y participación de los trabajadores
A61: =1+A58 -> 43 | B61: La organización debe establecer, implementar, mantener procesos para la consulta y la participación de los trabajadores a todos los niveles y funciones aplicables, y cuando exista, de los representantes de los trabajadores en el desarrollo, la planificación, la implementación, la evaluación del desempeño y las acciones para la mejora del SG-SST. | D61: =+IF(C61="","",+IF(C61=0,"No Cumple",+IF(C61=1,"Cumple Parcial",+IF(C61=2,"Cumple Completo",+IF(C61="N","NA")))))
A62: =1+A61 -> 44 | B62: La organización debe: a) proporcionar los mecanismos, el tiempo, la formación y los recursos necesarios para la consulta y la participación | D62: =+IF(C62="","",+IF(C62=0,"No Cumple",+IF(C62=1,"Cumple Parcial",+IF(C62=2,"Cumple Completo",+IF(C62="N","NA")))))
A63: =1+A62 -> 45 | B63: Nota 1: la representación de los trabajadores puede ser un mecanismo para la consulta y la participación.
A64: =1+A63 -> 46 | B64: b) proporcionar el acceso oportuno a información clara, comprensible y pertinente sobre el SG-SST | D64: =+IF(C64="","",+IF(C64=0,"No Cumple",+IF(C64=1,"Cumple Parcial",+IF(C64=2,"Cumple Completo",+IF(C64="N","NA")))))
A65: =1+A64 -> 47 | B65: c) determinar y eliminar los obstáculos o barreras a la participación y minimizar aquellas que no pueden eliminarse | D65: =+IF(C65="","",+IF(C65=0,"No Cumple",+IF(C65=1,"Cumple Parcial",+IF(C65=2,"Cumple Completo",+IF(C65="N","NA")))))
A66: =1+A65 -> 48 | B66: Nota 2: los obstáculos y las barreras pueden incluir la falta de respuesta a los aportes o sugerencias de los trabajadores, barreras de idioma o de alfabetización, represalias o amenazas de represalias y políticas o prácticas que desalientan o penalizan la participación del trabajador. | D66: =+IF(C66="","",+IF(C66=0,"No Cumple",+IF(C66=1,"Cumple Parcial",+IF(C66=2,"Cumple Completo",+IF(C66="N","NA")))))
A67: =1+A66 -> 49 | B67: d) enfatiza la consulta de los trabajadores no directivos sobre lo siguiente: 1) la determinación de las necesdades y expectativas de las partes interesadas (véase 4.2). 2) el establecimiento de la política de la SST (véase 5.2) 3) la asignación de roles y autoridades de la organización, según sea aplicable (véase 5.3) 4) la determinación de cómo cumplir los requisitos legales y otros requisitos (véase 6.1.3) 5) el establecimiento de los objetivos de la SST y la planificación para lograrlos (véase 6.2) 6) la determinación de los controles aplicables para la contratación externa, las compras y los contratistas (véase 8.1.4) 7) la determinación de qué necesita seguimiento, medición y evaluación (véase 9.1) 8) la planificación, el establecimiento, la implementación yle mantenimiento de programas de auditoría (véase 9.2.2). 9) el aseguramiento de la mejora continua (véase 10.3). | D67: =+IF(C67="","",+IF(C67=0,"No Cumple",+IF(C67=1,"Cumple Parcial",+IF(C67=2,"Cumple Completo",+IF(C67="N","NA")))))
A68: =1+A67 -> 50 | B68: e) enfatiza la participación de los trabajadores no dorectivos sobre lo siguiente: 1) la determinación de los mecanismos para su consulta y participación 2) la identificación de los peligros y la evaluación de los riesgos y oportunidades (véanse 6.1.1 y 6.1.2). 3) la determinación de las acciones para eliminar los peligros y reducir los riesgos para la SST (véase 6.1.4). 4) la determinación de los requisitos de competencia, las necesidades de formación, la formación y evaluación de la formación (véase 7.2). 5) la determinación de qué información se necesita comunicar y cómo hacerlo (véase 7.4). 6) la determinación de las medidas de control y su implementación y uso eficaces (véanse 8.1, 8.1.3 y 8.2). 7) la investigación de los incidentes y no conformidades y la determinación de las acciones correctivas (véase 10.2). | D68: =+IF(C68="","",+IF(C68=0,"No Cumple",+IF(C68=1,"Cumple Parcial",+IF(C68=2,"Cumple Completo",+IF(C68="N","NA")))))
A69: =1+A68 -> 51 | B69: Nota 3: Enfatizar la consulta y participación de los trabajadores no directivos pretende aplicarse a las personas que llevan a cabo actividades de trabajo, pero no pretende excluir, por ejemplo, a los directivos que sufren impacto por actividades de trabajo o por otros factores de la organización. | D69: =+IF(C69="","",+IF(C69=0,"No Cumple",+IF(C69=1,"Cumple Parcial",+IF(C69=2,"Cumple Completo",+IF(C69="N","NA")))))
A70: =1+A69 -> 52 | B70: Nota 4: Se reconoce que la provisión sin costo para los trabajadores y la provisión de formacion durante las horas de trabajo, cuando sea posible, pueden eliminar barreras significativas para la participación de los trabajadores. | D70: =+IF(C70="","",+IF(C70=0,"No Cumple",+IF(C70=1,"Cumple Parcial",+IF(C70=2,"Cumple Completo",+IF(C70="N","NA")))))
A71: =1+A70 -> 53 | B71: Esta cláusula pretende promover la participación de los trabajadores, el compromiso y las comunicaciones. También, promueve la participación de roles no directivos dentro de los requisitos del SG-SST, incluyendo incidentes investigaciones, evaluaciones de riesgos, más control y monitoreo actividades, incluida la auditoría interna. | D71: =+IF(C71="","",+IF(C71=0,"No Cumple",+IF(C71=1,"Cumple Parcial",+IF(C71=2,"Cumple Completo",+IF(C71="N","NA")))))
C72: =SUM(C61:C71) -> 0 | D72: =+COUNT(C61:C71)*2 -> 0 | E72: =+IF(C61="","",C72/D72) | G72: =+IF(E42="","",+AVERAGE(E42,E52,E59,E72))
A73: 6 | B73: PLANIFICACIÓN
A74: 6.1 | B74: Acciones para abordar riesgos y oportunidades
A75: 6.1.1 | B75: Generalidades
A76: =1+A71 -> 54 | B76: Al planificar el SG-SST, la organización debe considerar las cuestiones referidas en el apartado 4.1 (contexto), los requisitos referidos en los apartados 4.2 (partes interesadas y 4.3 (el alcance de su de SG-SST) y determinar los riesgos y oportunidades que es necesario abordar con el fin de: | D76: =+IF(C76="","",+IF(C76=0,"No Cumple",+IF(C76=1,"Cumple Parcial",+IF(C76=2,"Cumple Completo",+IF(C76="N","NA")))))
A77: =1+A76 -> 55 | B77: a) asegurar que el SG-SST puede alcanzar los resultados previstos | D77: =+IF(C77="","",+IF(C77=0,"No Cumple",+IF(C77=1,"Cumple Parcial",+IF(C77=2,"Cumple Completo",+IF(C77="N","NA")))))
A78: =1+A77 -> 56 | B78: b) prevenir o reducir efectos no deseados | D78: =+IF(C78="","",+IF(C78=0,"No Cumple",+IF(C78=1,"Cumple Parcial",+IF(C78=2,"Cumple Completo",+IF(C78="N","NA")))))
A79: =1+A78 -> 57 | B79: c) lograr la mejora continua | D79: =+IF(C79="","",+IF(C79=0,"No Cumple",+IF(C79=1,"Cumple Parcial",+IF(C79=2,"Cumple Completo",+IF(C79="N","NA")))))
A80: =1+A79 -> 58 | B80: Al determinar los riesgos y oportunidades para el SG-SST y sus resultados previstos que es necesario abordar, la organización debe tener en cuenta: · los peligros (véase 6.1.2.1) · los riesgos para la SST y otros riesgos (véase 6.1.2.2) · las oportunidades para la SST y otras oportunidades (véase 6.1.2.3) · los requisitos legales y otros requisitos (véase 6.1.3) | D80: =+IF(C80="","",+IF(C80=0,"No Cumple",+IF(C80=1,"Cumple Parcial",+IF(C80=2,"Cumple Completo",+IF(C80="N","NA")))))
A81: =1+A80 -> 59 | B81: La organización, en sus procesos de planificación, debe determinar y evaluar los riesgos y oportunidades que son pertinentes para los resultados previstos del SG-SST asociados con los cambios en la organización, sus procesos, o el SG-SST. En el caso de cambios planificados, permanentes o temporales, esta evaluación debe llevarse a cabo antes de que se implemente el cambio (vésase 8.1.3) | D81: =+IF(C81="","",+IF(C81=0,"No Cumple",+IF(C81=1,"Cumple Parcial",+IF(C81=2,"Cumple Completo",+IF(C81="N","NA")))))
A82: =1+A81 -> 60 | B82: La organización debe mantener información documentada sobre: · Los riesgos y oportunidades · los procesos y acciones necesarios para determinar y abordar sus riesgos y oportunidades (vésase desde 6.1.2 hasta 6.1.4), en la medida necesaria para tener la confianza de que se llevan a cabo según lo planificado. | D82: =+IF(C82="","",+IF(C82=0,"No Cumple",+IF(C82=1,"Cumple Parcial",+IF(C82=2,"Cumple Completo",+IF(C82="N","NA")))))
A83: =1+A82 -> 61 | B83: Asegurar que los riesgos y las oportunidades de 4.1 están documentados y que las acciones se han definido para aprovechar las oportunidades y mitigar los riesgos asociados con el SG-SST. Demuestre que estas acciones han sido efectivas. Esta Información debe estar disponible como información documentada. | D83: =+IF(C83="","",+IF(C83=0,"No Cumple",+IF(C83=1,"Cumple Parcial",+IF(C83=2,"Cumple Completo",+IF(C83="N","NA")))))
C84: =SUM(C76:C78) -> 0 | D84: =+COUNT(C76:C78)*2 -> 0 | E84: =+IF(C76="","",C84/D84)
A85: 6.1.2 | B85: Identificación de peligros y evaluación de riesgos y oportunidades
A86: 6.1.2.1 | B86: Identificación de peligros
A87: =1+A83 -> 62 | B87: La organización debe establecer, implementar y matener procesos de identificación continua y proactiva de los peligros. Los procesos deben tener en cuenta, pero no limitarse a: | D87: =+IF(C87="","",+IF(C87=0,"No Cumple",+IF(C87=1,"Cumple Parcial",+IF(C87=2,"Cumple Completo",+IF(C87="N","NA")))))
A88: =1+A87 -> 63 | B88: a) cómo se organiza el trabajo, los factores sociales [incluyendo la carga de trabajo, horas de trabajo, victimización y acoso (bullying)) e intimidación], el liderazgo, la cultura de la organización | D88: =+IF(C88="","",+IF(C88=0,"No Cumple",+IF(C88=1,"Cumple Parcial",+IF(C88=2,"Cumple Completo",+IF(C88="N","NA")))))
A89: =1+A88 -> 64 | B89: b) las actividades y lsas situaciones rutinarias y no rutinarias, incluyendo los peligros que surjan de: 1) la infraestructura, los equipos, los materiales, las sustancias y las condiciones físicas del lugar de trabajo 2) el diseño de productos y servicios, la investigación, el desarrollo, los ensayos, la producción, el montaje, la construcción, la prestación de servicios, el mantenimiento y la disposición 3) los factores humanos 4) cómo se realiza el trabajo | D89: =+IF(C89="","",+IF(C89=0,"No Cumple",+IF(C89=1,"Cumple Parcial",+IF(C89=2,"Cumple Completo",+IF(C89="N","NA")))))
A90: =1+A89 -> 65 | B90: c) los incidentes pasados pertinentes internos o externos a la organización, incluyendo emergencias, y sus causas | D90: =+IF(C90="","",+IF(C90=0,"No Cumple",+IF(C90=1,"Cumple Parcial",+IF(C90=2,"Cumple Completo",+IF(C90="N","NA")))))
A91: =1+A90 -> 66 | B91: d) las situaciones de emergencia potenciales | D91: =+IF(C91="","",+IF(C91=0,"No Cumple",+IF(C91=1,"Cumple Parcial",+IF(C91=2,"Cumple Completo",+IF(C91="N","NA")))))
A92: =1+A91 -> 67 | B92: e) las personas, incluyendo la consideración de: 1) aquéllas con acceso al lugar de trabajo y sus actividades, incluyendo trabajadores, contratistas, visitantes y otras personas 2) aquéllas en las inmediaciones del lugar de trabajo que pueden verse afectadas por las actividades de la organización 3) los trabajadores en una ubicación que no está bajo el control directo de la organización | D92: =+IF(C92="","",+IF(C92=0,"No Cumple",+IF(C92=1,"Cumple Parcial",+IF(C92=2,"Cumple Completo",+IF(C92="N","NA")))))
A93: =1+A92 -> 68 | B93: f) otras cuestiones, incluyendo consideraciones de: 1) el diseño de las áreas de trabajo, los procesos, las instalaciones, la máquina/ equipos, los procedimientos operativos y la organización del trabajo, incluyendo su adaptación a las necesidades y capacidades de los trabajadores involucrados 2) las situaciones que ocurren en las inmediaciones del lugar de trabajo causadas por las actividades relacionadas con el trabajo bajo el control de la organización. 3) las situaciones no controladas por la organización y que ocurren en las inmediaciones del lugar de trabajo que pueden causar lesiones y deterioro de la salud de las personas en el lugar de trabajo. | D93: =+IF(C93="","",+IF(C93=0,"No Cumple",+IF(C93=1,"Cumple Parcial",+IF(C93=2,"Cumple Completo",+IF(C93="N","NA")))))
A94: =1+A93 -> 69 | B94: g) los cambios reales o propuestos en la organización, operaciones, procesos, actividades y el SG-SST. | D94: =+IF(C94="","",+IF(C94=0,"No Cumple",+IF(C94=1,"Cumple Parcial",+IF(C94=2,"Cumple Completo",+IF(C94="N","NA")))))
A95: =1+A94 -> 70 | B95: h) los cambios en el conocimiento y la información sobre los peligros | D95: =+IF(C95="","",+IF(C95=0,"No Cumple",+IF(C95=1,"Cumple Parcial",+IF(C95=2,"Cumple Completo",+IF(C95="N","NA")))))
A96: =1+A95 -> 71 | B96: Asegúrese de que el proceso de identificación de peligros de la organización considera: 1. Actividades y situaciones fuera de rutina y no rutinarias; 2. Factores humanos; 3. Nuevos peligros o cambios; 4. Situaciones de emergencia potenciales; 5. Personas; 6. Cambios en conocimiento e información sobre los peligros. En 6.1.1, hay un nuevo requisito para identificar oportunidades, como también: 1. Consideración de los trabajadores en un lugar que no está bajo el control directo de la organización; 2. Consideración de aquellos en las proximidades del lugar de trabajo que pueden verse afectados por las actividades de la organización; 3. Otras cuestiones, incluyendo situaciones no controladas por la organización y que ocurren en las cercanías del lugar de trabajo que pueden causar daño a la salud o enfermedad relacionados con el trabajo. | D96: =+IF(C96="","",+IF(C96=0,"No Cumple",+IF(C96=1,"Cumple Parcial",+IF(C96=2,"Cumple Completo",+IF(C96="N","NA")))))
C97: =SUM(C87:C96) -> 0 | D97: =+COUNT(C87:C96)*2 -> 0 | E97: =+IF(C87="","",C97/D97)
A98: 6.1.2.2 | B98: Evaluación de los riesgos para la SST y otros riesgos para el SG-SST
A99: =1+A96 -> 72 | B99: La organización debe establecer, implementar y matener procesos para: a) evaluar los riesgos para la SST apartir de los peligros identificados, teniendo en cuenta la eficacia de los controles existentes | D99: =+IF(C99="","",+IF(C99=0,"No Cumple",+IF(C99=1,"Cumple Parcial",+IF(C99=2,"Cumple Completo",+IF(C99="N","NA")))))
B100: b) determinar y evaluar los otros riesgos relacionados con el establecimiento, implementación, operación y mantenimiento del SG-SST | D100: =+IF(C100="","",+IF(C100=0,"No Cumple",+IF(C100=1,"Cumple Parcial",+IF(C100=2,"Cumple Completo",+IF(C100="N","NA")))))
...
